vehicle_dynamics/VehicleDynamics.py
vehicle_dynamics/__init__.py
vehicle_dynamics/main.py
vehicle_dynamics/modules/LocalLogger.py
vehicle_dynamics/modules/__init__.py
vehicle_dynamics/modules/body.py
vehicle_dynamics/modules/powertrain.py
vehicle_dynamics/modules/wheels.py
vehicle_dynamics/structures/AngularWheelPosition.py
vehicle_dynamics/structures/CurrentStates.py
vehicle_dynamics/structures/Displacement.py
vehicle_dynamics/structures/Manoeuvre.py
vehicle_dynamics/structures/OutputStates.py
vehicle_dynamics/structures/StateVector.py
vehicle_dynamics/structures/StaticParameters.py
vehicle_dynamics/structures/StrutForce.py
vehicle_dynamics/structures/TireForces.py
vehicle_dynamics/structures/WheelHubForce.py
vehicle_dynamics/structures/__init__.py
vehicle_dynamics/utils/CurrentStates.py
vehicle_dynamics/utils/LocalLogger.py
vehicle_dynamics/utils/StaticParameters.py
vehicle_dynamics/utils/__init__.py
vehicle_dynamics/utils/import_data_CM.py
vehicle_dynamics/utils/plot_function.py
vehicle_dynamics-1.0.7.dist-info/LICENSE
vehicle_dynamics-1.0.7.dist-info/METADATA
vehicle_dynamics-1.0.7.dist-info/WHEEL
vehicle_dynamics-1.0.7.dist-info/top_level.txt
vehicle_dynamics-1.0.7.dist-info/RECORD
