Metadata-Version: 2.1
Name: vehicle_dynamics
Version: 1.0.7
Summary: Python Package that makes Vehicle Dynamics Calculation for cars. 
Author: Maikol Funk Dreschler, Yuri Poledna
Author-email: Yuri Poledna <yuri.poledna@carissma.eu>
License: MIT
Project-URL: Homepage, https://github.com/roadview-project/vehicle-dynamics
Project-URL: Repository, https://github.com/roadview-project/vehicle-dynamics
Requires-Python: >=3.7
License-File: LICENSE
Requires-Dist: numpy
Requires-Dist: matplotlib
Requires-Dist: scipy
Requires-Dist: pyyaml
Requires-Dist: tqdm
Requires-Dist: pandas
Requires-Dist: munch
